<annotation>
	<folder>images</folder>
	<filename>761.jpg</filename>
	<path>/content/Project/images/train/train/761.jpg</path>
	<source>
		<database>Unknown</database>
	</source>
	<size>
		<width>128</width>
		<height>128</height>
		<depth>3</depth>
	</size>
	<segmented>0</segmented>
	<object>
		<name>Cellulitis</name>
		<pose>Unspecified</pose>
		<truncated>0</truncated>
		<difficult>0</difficult>
		<bndbox>
			<xmin>40</xmin>
			<ymin>69</ymin>
			<xmax>68</xmax>
			<ymax>91</ymax>
		</bndbox>
	</object>
	<object>
		<name>Cellulitis</name>
		<pose>Unspecified</pose>
		<truncated>0</truncated>
		<difficult>0</difficult>
		<bndbox>
			<xmin>93</xmin>
			<ymin>106</ymin>
			<xmax>107</xmax>
			<ymax>122</ymax>
		</bndbox>
	</object>
	<object>
		<name>Cellulitis</name>
		<pose>Unspecified</pose>
		<truncated>0</truncated>
		<difficult>0</difficult>
		<bndbox>
			<xmin>66</xmin>
			<ymin>6</ymin>
			<xmax>84</xmax>
			<ymax>43</ymax>
		</bndbox>
	</object>
</annotation>